{
  "api": {
    "name": "AccountManagerPlugin",
    "slug": "accountmanagerplugin",
    "docs": "",
    "tags": [],
    "methods": [
      {
        "name": "getAccount",
        "signature": "() => Promise<{}>",
        "parameters": [],
        "returns": "Promise<{}>",
        "tags": [],
        "docs": "",
        "complexTypes": [],
        "slug": "getaccount"
      },
      {
        "name": "addNewAccount",
        "signature": "(options: { accountType: string; authTokenType: string; }) => Promise<void>",
        "parameters": [
          {
            "name": "options",
            "docs": "",
            "type": "{ accountType: string; authTokenType: string; }"
          }
        ],
        "returns": "Promise<void>",
        "tags": [],
        "docs": "",
        "complexTypes": [],
        "slug": "addnewaccount"
      },
      {
        "name": "getExistingAccountAuthToken",
        "signature": "(options: { userName: string; authTokenType: string; }) => Promise<void>",
        "parameters": [
          {
            "name": "options",
            "docs": "",
            "type": "{ userName: string; authTokenType: string; }"
          }
        ],
        "returns": "Promise<void>",
        "tags": [],
        "docs": "",
        "complexTypes": [],
        "slug": "getexistingaccountauthtoken"
      },
      {
        "name": "showAccountPicker",
        "signature": "() => Promise<void>",
        "parameters": [],
        "returns": "Promise<void>",
        "tags": [],
        "docs": "",
        "complexTypes": [],
        "slug": "showaccountpicker"
      },
      {
        "name": "getTokenForAccountCreateIfNeeded",
        "signature": "(options: { accountType: string; authTokenType: string; }) => Promise<void>",
        "parameters": [
          {
            "name": "options",
            "docs": "",
            "type": "{ accountType: string; authTokenType: string; }"
          }
        ],
        "returns": "Promise<void>",
        "tags": [],
        "docs": "",
        "complexTypes": [],
        "slug": "gettokenforaccountcreateifneeded"
      },
      {
        "name": "invalidateAuthToken",
        "signature": "() => Promise<void>",
        "parameters": [],
        "returns": "Promise<void>",
        "tags": [],
        "docs": "",
        "complexTypes": [],
        "slug": "invalidateauthtoken"
      },
      {
        "name": "authenticator",
        "signature": "(options: { userName: string; AccountType: string; }) => Promise<void>",
        "parameters": [
          {
            "name": "options",
            "docs": "",
            "type": "{ userName: string; AccountType: string; }"
          }
        ],
        "returns": "Promise<void>",
        "tags": [],
        "docs": "",
        "complexTypes": [],
        "slug": "authenticator"
      },
      {
        "name": "accountPicker",
        "signature": "() => Promise<authData>",
        "parameters": [],
        "returns": "Promise<authData>",
        "tags": [],
        "docs": "",
        "complexTypes": [
          "authData"
        ],
        "slug": "accountpicker"
      }
    ],
    "properties": []
  },
  "interfaces": [
    {
      "name": "authData",
      "slug": "authdata",
      "docs": "",
      "tags": [],
      "methods": [],
      "properties": [
        {
          "name": "authAccount",
          "tags": [],
          "docs": "",
          "complexTypes": [],
          "type": "string"
        },
        {
          "name": "sourcedId",
          "tags": [],
          "docs": "",
          "complexTypes": [],
          "type": "string"
        },
        {
          "name": "endpointUrl",
          "tags": [],
          "docs": "",
          "complexTypes": [],
          "type": "string"
        },
        {
          "name": "addedType",
          "tags": [],
          "docs": "",
          "complexTypes": [],
          "type": "string"
        },
        {
          "name": "authToken",
          "tags": [],
          "docs": "",
          "complexTypes": [],
          "type": "string"
        }
      ]
    }
  ],
  "enums": [],
  "typeAliases": [],
  "pluginConfigs": []
}